<PAMDataset>
  <PAMRasterBand band="1">
    <Description>lyr.1</Description>
    <Histograms>
      <HistItem>
        <HistMin>0.01957329362630844</HistMin>
        <HistMax>2.686741352081299</HistMax>
        <BucketCount>256</BucketCount>
        <IncludeOutOfRange>1</IncludeOutOfRange>
        <Approximate>0</Approximate>
        <HistCounts>197|2433|7991|13387|15504|21195|27381|29576|31391|31313|30425|27540|24584|23570|21738|20102|18728|18366|17005|15700|14991|13647|12263|11550|10470|8727|8006|7410|6563|6063|5588|5243|5034|4961|4887|4727|4762|4875|4993|4968|5076|5191|5301|5583|5832|5928|6148|6252|6575|6771|7067|7122|7145|7343|7446|7418|7560|7317|7494|7294|7275|7184|7170|7046|6900|6732|6681|6393|6371|6265|6163|6059|5760|5532|5402|5181|4970|4873|4748|4570|4384|4298|4023|3981|3827|3623|3522|3437|3376|3150|3193|3211|3127|3126|2998|2944|2613|2737|2676|2569|2747|2570|2586|2532|2611|2475|2479|2421|2358|2275|2180|2067|2004|1925|1904|1718|1789|1718|1726|1669|1550|1563|1512|1432|1369|1367|1242|1214|1203|1107|981|997|980|895|820|817|833|795|786|727|684|643|707|544|573|607|518|502|482|485|455|449|410|373|401|350|364|368|358|368|397|341|343|316|349|320|323|311|260|265|265|235|222|233|186|193|201|201|182|182|184|147|152|156|125|123|129|135|112|129|113|118|91|94|93|89|72|87|70|71|62|66|55|57|38|57|48|42|57|45|48|25|40|40|35|26|35|27|23|18|19|24|18|24|18|21|17|21|17|12|5|7|11|5|3|2|3|4|4|1|1|0|5|2|4|3|3|2|3|3|2|1|2|0|0|1</HistCounts>
      </HistItem>
    </Histograms>
    <Metadata>
      <MDI key="STATISTICS_MINIMUM">0.019573293626308</MDI>
      <MDI key="STATISTICS_MAXIMUM">2.6867413520813</MDI>
      <MDI key="STATISTICS_MEAN">0.46088252166891</MDI>
      <MDI key="STATISTICS_STDDEV">0.39075004649901</MDI>
      <MDI key="STATISTICS_MEDIAN">0.291520</MDI>
      <MDI key="STATISTICS_COUNT">952119.000000</MDI>
      <MDI key="STATISTICS_SKIPFACTORX">1</MDI>
      <MDI key="STATISTICS_SKIPFACTORY">1</MDI>
      <MDI key="STATISTICS_EXCLUDEDVALUES"></MDI>
      <MDI key="STATISTICS_COVARIANCES">0.1526855988389787</MDI>
    </Metadata>
  </PAMRasterBand>
</PAMDataset>
